pybif6-0.1.3.dist-info/METADATA
pybif6-0.1.3.dist-info/WHEEL
pybif6-0.1.3.dist-info/entry_points.txt
pybif6-0.1.3.dist-info/licenses/COPYING
pybif6/__init__.py
pybif6/parser.py
pybif6-0.1.3.dist-info/RECORD
