Metadata-Version: 2.1
Name: pybif6
Version: 0.1.3
Summary: ToF-SIMS BIF6 file parsing library
Author-Email: Shenghui Ye <yesh@aliyun.com>
License: GPL-3
Project-URL: Homepage, https://github.com/yesh0/pybif6
Project-URL: Issues, https://github.com/yesh0/pybif6/issues
Requires-Python: >=3.9
Requires-Dist: numpy>=1.20
